sorting_vis/__init__.py
sorting_vis/__main__.py
sorting_vis/algorithms.py
sorting_vis/bare_algorithms.py
sorting_vis/config.ini
sorting_vis/constants.py
sorting_vis/gui.py
sorting_vis/assets/TrojanBlue.json
sorting_vis/assets/gasp.png
sorting_vis/assets/sorting_vis.png
sorting_vis/assets/thumbs_up.png
sorting_vis-2.0.1.dist-info/METADATA
sorting_vis-2.0.1.dist-info/WHEEL
sorting_vis-2.0.1.dist-info/entry_points.txt
sorting_vis-2.0.1.dist-info/top_level.txt
sorting_vis-2.0.1.dist-info/RECORD
